<?xml version="1.0"?>
<subtitles>
  <subtitle id="0">
    <StartTime>4</StartTime>
    <Text>這大宅內的日落餘暉是我見過最悲傷的事物了。</Text>
  </subtitle>
  <subtitle id="1">
    <StartTime>11.5</StartTime>
    <Text>我只想好好睡個覺。</Text>
  </subtitle>
  <subtitle id="2">
    <StartTime>14.75</StartTime>
  <Text>當我在閣樓裡，我幾乎感到蘭妮似乎還在這⋯⋯就在樓下⋯⋯我只在等著聽見她拉下閣樓樓梯跑上來的聲音。</Text>
  </subtitle>
  <subtitle id="3">
    <StartTime>27</StartTime>
    <Text>或許我該上閣樓⋯⋯然後等待⋯⋯</Text>
  </subtitle>
  <subtitle id="4">
    <StartTime>31</StartTime>
    <Text></Text>
  </subtitle>
  </subtitles>